{
  "name": "base_ts40",
  "data": [
    {
      "seriesName": "PRC_ELC_COA",
      "seriesValues": [
        [
          2021,
          3.344939337202976
        ],
        [
          2023,
          0.0134218726268714
        ]
      ]
    },
    {
      "seriesName": "PRC_ELC_GAS",
      "seriesValues": [
        [
          2024,
          47.54180324587615
        ],
        [
          2025,
          0.0223405561263262
        ]
      ]
    },
    {
      "seriesName": "PRC_ELC_WNO",
      "seriesValues": [
        [
          2025,
          100.79544249177917
        ],
        [
          2026,
          64.37356127500013
        ],
        [
          2027,
          49.50928528281014
        ],
        [
          2028,
          46.78729087411556
        ],
        [
          2029,
          58.20105502884879
        ],
        [
          2030,
          65.9348232534987
        ],
        [
          2031,
          40.416748665763876
        ],
        [
          2032,
          38.56480781155444
        ],
        [
          2033,
          24.95188565344175
        ],
        [
          2034,
          25.48886831112239
        ],
        [
          2035,
          39.0953225973565
        ],
        [
          2036,
          35.94988599327042
        ],
        [
          2037,
          37.21235706177265
        ],
        [
          2038,
          31.026842278524867
        ],
        [
          2039,
          58.4303331432654
        ],
        [
          2040,
          51.87277505424506
        ],
        [
          2041,
          60.04621482323659
        ],
        [
          2042,
          50.94064365342145
        ],
        [
          2043,
          60.674455881521105
        ],
        [
          2044,
          42.587395655324414
        ],
        [
          2045,
          46.45868666051219
        ],
        [
          2046,
          47.410438491678484
        ],
        [
          2047,
          52.67072718041403
        ],
        [
          2048,
          36.67545418409131
        ],
        [
          2049,
          71.36199260807165
        ],
        [
          2050,
          94.18426568813392
        ]
      ]
    },
    {
      "seriesName": "PRC_ELC_SPV",
      "seriesValues": [
        [
          2028,
          49.55324641296048
        ],
        [
          2029,
          59.53730293534436
        ],
        [
          2030,
          86.91732944761144
        ],
        [
          2031,
          83.4008552064
        ],
        [
          2032,
          95.44082250376641
        ],
        [
          2033,
          87.5149115178514
        ],
        [
          2034,
          51.243184275215
        ],
        [
          2035,
          28.602577273338184
        ],
        [
          2036,
          24.95865497322547
        ],
        [
          2037,
          15.97773544125283
        ],
        [
          2038,
          11.522638964453282
        ],
        [
          2039,
          16.367157273958842
        ],
        [
          2040,
          21.97564842294655
        ],
        [
          2041,
          13.742880784074936
        ],
        [
          2042,
          4.938332578769343
        ],
        [
          2043,
          13.694701937556239
        ],
        [
          2044,
          5.082652798657523
        ],
        [
          2045,
          3.147848145227786
        ],
        [
          2046,
          4.849778858985146
        ],
        [
          2047,
          6.706093434286062
        ],
        [
          2048,
          11.374825146602628
        ],
        [
          2049,
          20.983340148340776
        ],
        [
          2050,
          17.5587152584345
        ]
      ]
    }
  ]
}